[1,["00Icta5PBHCbC2XiGHVyC3@6c48a","1awEnXyJlJKomnTo2Fzkyx@6c48a","a2ABhWJPVKx5MJEgejIQzY@6c48a","00Icta5PBHCbC2XiGHVyC3@f9941","a2ABhWJPVKx5MJEgejIQzY@f9941","1awEnXyJlJKomnTo2Fzkyx@f9941"],["node","_textureSource","_spriteFrame","_barSprite","data","_parent"],[["cc.Node",["_name","_layer","_components","_prefab","_children","_lpos","_parent"],1,9,4,2,5,1],"cc.SpriteFrame",["cc.UITransform",["_name","node","__prefab","_contentSize"],2,1,4,5],["cc.Sprite",["_name","_type","_sizeMode","node","__prefab","_spriteFrame"],0,1,4,6],["cc.Widget",["_alignFlags","_bottom","_originalWidth","_originalHeight","node","__prefab"],-1,1,4],["545c05XsG9GDJispEGWKvYv",["watchPathArr","watchPath","templateMode","node","__prefab"],0,1,4],["cc.Prefab",["_name"],2],["cc.Node",["_name","_layer","_parent","_components","_prefab"],1,1,12,4],["cc.CompPrefabInfo",["fileId"],2],["cc.ProgressBar",["_mode","_progress","node","__prefab","_barSprite"],1,1,4,1],["2a50eqI7JZNV5Sh0y/Qd9C6",["componentName","componentProperty","watchPathArr","node","__prefab"],0,1,4],["cc.PrefabInfo",["root","fileId","asset"],1,1],["92429ykTnxFCrcGyW58JWjj",["node","__prefab"],3,1,4],["f64deiQLAhLh5HGqUqaI9oA",["node","__prefab"],3,1,4],["cc.Label",["_name","_string","_actualFontSize","_isBold","node","__prefab"],-1,1,4],["cc.LabelOutline",["node","__prefab"],3,1,4]],[[8,0,2],[11,0,1,2,3],[2,0,1,2,3,2],[0,0,1,6,2,3,5,3],[2,1,2,3,1],[3,3,4,5,1],[14,0,1,2,3,4,5,5],[15,0,1,1],[6,0,2],[0,0,1,4,2,3,5,3],[0,0,1,4,2,3,3],[0,0,1,6,2,3,3],[7,0,1,2,3,4,3],[3,0,1,2,3,4,4],[9,0,1,2,3,4,3],[10,0,1,2,3,4,4],[4,0,1,4,5,3],[4,0,2,3,4,5,4],[12,0,1,1],[13,0,1,1],[5,1,0,3,4,3],[5,2,0,3,4,3]],[[[{"name":"bg","rect":{"x":0,"y":0,"width":1600,"height":720},"offset":{"x":0,"y":0},"originalSize":{"width":1600,"height":720},"rotated":false,"capInsets":[0,0,0,0],"packable":true}],[1],0,[0],[1],[0]],[[{"name":"icon_loading_bar","rect":{"x":0,"y":0,"width":549,"height":47},"offset":{"x":0,"y":0},"originalSize":{"width":549,"height":47},"rotated":false,"capInsets":[0,0,0,0],"packable":true}],[1],0,[0],[1],[1]],[[{"name":"panel_loading_bottom_frame","rect":{"x":0,"y":0,"width":567,"height":65},"offset":{"x":0,"y":0},"originalSize":{"width":567,"height":65},"rotated":false,"capInsets":[0,0,0,0],"packable":true}],[1],0,[0],[1],[2]],[[[8,"loading"],[9,"pro_progress",33554432,[-7,-8,-9],[[4,-1,[0,"82bjtghDJB8YqPMxJfJ5Rr"],[5,567,65]],[5,-2,[0,"c6r2/EbkJLgZKG1NvbxXiz"],1],[14,2,0,-4,[0,"d8F8xTDrRJ2aYLMRDN1Csc"],-3],[15,"cc.ProgressBar","progress",["*.finished","*.total"],-5,[0,"8cfgfLAqtIJLDNqIgFd8Xt"]],[16,4,80,-6,[0,"7cjLANFmdN6aV+qs7kuNy2"]]],[1,null,"ecgn8y3TJCyrNvvrmyHnya",0],[1,0,-247.5,0]],[10,"loading",33554432,[-14,1],[[2,"loading<UITransform>",-10,[0,"dcwRyrrAFJIZu8cg5N9Q7q"],[5,1280,720]],[17,45,1280,720,-11,[0,"26ZokSfFxPFr+5cT88/8nR"]],[18,-12,[0,"daCFe+B0BOeZtHLHqBYu9Z"]],[19,-13,[0,"e7e6p2rm9FyqgwsK8M/BUH"]]],[1,null,"65Pe/9AIJMgIjcSkJv5QHh",0]],[3,"lab_prompt",33554432,1,[[2,"lab_progress<UITransform>",-15,[0,"37WpHB35ZA8KJNfmflUmio"],[5,164,54.4]],[6,"lab_progress<Label>","状态提示",40,true,-16,[0,"18xXPm7ZRGtJOVkw0KWRyI"]],[7,-17,[0,"bfTjeen/RO8Z25U0XoQYb0"]],[20,"*.prompt",[""],-18,[0,"aaLLLRoNxJM6JIqIOxEbdK"]]],[1,null,"a4Hlk39nNMV7QG9p+cKfSl",0],[1,0,74.13,0]],[3,"lab_progress",33554432,1,[[2,"lab_progress<UITransform>",-19,[0,"59IJ+5vLRHKrxqAzljTkOL"],[5,124.08,54.4]],[6,"lab_progress<Label>","{{0}}%",40,true,-20,[0,"fcepWL0LBALrW5rf6BD7MO"]],[7,-21,[0,"6auaUje5JKw65o5hEPEyWR"]],[21,true,["*.progress"],-22,[0,"daILjufOlPdqRfYp3C/iqc"]]],[1,null,"8ebP9wp/lHdpbk2hOCdLkX",0],[1,0,-67.3,0]],[11,"bg",33554432,2,[[4,-23,[0,"f7NISe7HdAD68SLfhnddy8"],[5,1600,720]],[5,-24,[0,"e71ctEmpxFC4KlSYRZNz/a"],0]],[1,null,"7cza7A3O1NDLUuQQdasqMx",0]],[12,"pro_bar",33554432,1,[[[2,"Sprite<UITransform>",-25,[0,"bexms9rIVO1aqwsiKpx7p+"],[5,549,47]],-26],4,1],[1,null,"3dI6CU5MVPS4+WmiQzY0D3",0]],[13,"Sprite<Sprite>",3,2,6,[0,"0fN5X9mM5MyL1PjGl22OSC"]]],0,[0,0,1,0,0,1,0,3,7,0,0,1,0,0,1,0,0,1,0,-1,3,0,-2,6,0,-3,4,0,0,2,0,0,2,0,0,2,0,0,2,0,-1,5,0,0,3,0,0,3,0,0,3,0,0,3,0,0,4,0,0,4,0,0,4,0,0,4,0,0,5,0,0,5,0,0,6,0,-2,7,0,4,2,1,5,2,26],[0,0,7],[2,2,2],[3,4,5]]]]
